selectel/__init__.py
selectel/storage.py
selectel_api-0.1.5.dist-info/DESCRIPTION.rst
selectel_api-0.1.5.dist-info/METADATA
selectel_api-0.1.5.dist-info/RECORD
selectel_api-0.1.5.dist-info/WHEEL
selectel_api-0.1.5.dist-info/metadata.json
selectel_api-0.1.5.dist-info/top_level.txt
