Metadata-Version: 2.0
Name: selectel-api
Version: 0.1.5
Summary: Simple selectel API
Home-page: https://github.com/go1dshtein/selectel-api
Author: Kirill Goldshtein
Author-email: goldshtein.kirill@gmail.com
License: MIT
Platform: UNKNOWN
Classifier: Intended Audience :: Developers
Classifier: Topic :: Software Development :: Libraries
Classifier: Development Status :: 3 - Alpha
Classifier: Programming Language :: Python
Classifier: Programming Language :: Python :: 2.7
Classifier: Programming Language :: Python :: 3.3
Classifier: Programming Language :: Python :: 3.4
Requires-Dist: requests (>=1.2.1)
